{
  "main": {
    "id": "8126705a69b02ac7",
    "type": "split",
    "children": [
      {
        "id": "ce09c1c7d140c4e2",
        "type": "tabs",
        "children": [
          {
            "id": "f118e42fbfe406e6",
            "type": "leaf",
            "state": {
              "type": "markdown",
              "state": {
                "file": "Others/Powerpoint Addin's.md",
                "mode": "source",
                "source": false
              },
              "icon": "lucide-file",
              "title": "Powerpoint Addin's"
            }
          },
          {
            "id": "4da6d47efee0d28b",
            "type": "leaf",
            "state": {
              "type": "empty",
              "state": {},
              "icon": "lucide-file",
              "title": "New tab"
            }
          },
          {
            "id": "b21145a5e7e0785a",
            "type": "leaf",
            "state": {
              "type": "canvas",
              "state": {
                "file": "Engine/Engine.Core/FQDN.canvas",
                "viewState": {
                  "x": -162.03887276690944,
                  "y": 133.06638522742975,
                  "zoom": -0.12332071660761079
                }
              },
              "icon": "lucide-layout-dashboard",
              "title": "FQDN"
            }
          }
        ],
        "currentTab": 2
      }
    ],
    "direction": "vertical"
  },
  "left": {
    "id": "dd3f4c5d450c5f3d",
    "type": "split",
    "children": [
      {
        "id": "68318f316cad6e67",
        "type": "tabs",
        "children": [
          {
            "id": "80a060ffd7fb1ac9",
            "type": "leaf",
            "state": {
              "type": "file-explorer",
              "state": {
                "sortOrder": "alphabetical",
                "autoReveal": false
              },
              "icon": "lucide-folder-closed",
              "title": "Files"
            }
          },
          {
            "id": "fcaec59d94bdba5e",
            "type": "leaf",
            "state": {
              "type": "search",
              "state": {
                "query": "",
                "matchingCase": false,
                "explainSearch": false,
                "collapseAll": false,
                "extraContext": false,
                "sortOrder": "alphabetical"
              },
              "icon": "lucide-search",
              "title": "Search"
            }
          },
          {
            "id": "715c55a067077e8e",
            "type": "leaf",
            "state": {
              "type": "bookmarks",
              "state": {},
              "icon": "lucide-bookmark",
              "title": "Bookmarks"
            }
          }
        ]
      }
    ],
    "direction": "horizontal",
    "width": 316.49999618530273
  },
  "right": {
    "id": "e7aa00dae9662fc9",
    "type": "split",
    "children": [
      {
        "id": "c47bd8d6970ea9c1",
        "type": "tabs",
        "children": [
          {
            "id": "a116fe5264d11f1f",
            "type": "leaf",
            "state": {
              "type": "backlink",
              "state": {
                "collapseAll": false,
                "extraContext": false,
                "sortOrder": "alphabetical",
                "showSearch": false,
                "searchQuery": "",
                "backlinkCollapsed": false,
                "unlinkedCollapsed": true
              },
              "icon": "links-coming-in",
              "title": "Backlinks"
            }
          },
          {
            "id": "ff6bfb8cb9f959c9",
            "type": "leaf",
            "state": {
              "type": "outgoing-link",
              "state": {
                "linksCollapsed": false,
                "unlinkedCollapsed": true
              },
              "icon": "links-going-out",
              "title": "Outgoing links"
            }
          },
          {
            "id": "08396d527f8412c8",
            "type": "leaf",
            "state": {
              "type": "tag",
              "state": {
                "sortOrder": "frequency",
                "useHierarchy": true,
                "showSearch": false,
                "searchQuery": ""
              },
              "icon": "lucide-tags",
              "title": "Tags"
            }
          },
          {
            "id": "ce4f30dd2ee3498e",
            "type": "leaf",
            "state": {
              "type": "outline",
              "state": {
                "followCursor": false,
                "showSearch": false,
                "searchQuery": ""
              },
              "icon": "lucide-list",
              "title": "Outline"
            }
          }
        ]
      }
    ],
    "direction": "horizontal",
    "width": 300,
    "collapsed": true
  },
  "left-ribbon": {
    "hiddenItems": {
      "switcher:Open quick switcher": false,
      "graph:Open graph view": false,
      "canvas:Create new canvas": false,
      "daily-notes:Open today's daily note": false,
      "templates:Insert template": false,
      "command-palette:Open command palette": false
    }
  },
  "active": "b21145a5e7e0785a",
  "lastOpenFiles": [
    "Engine/Engine.Core/DsSystem.md",
    "Engine/Engine.Core/DsCPU.md",
    "Engine/Engine.Core/Core Dll hierarchy.canvas",
    "Engine/Engine.Core/Core 자료 구조.md",
    "Engine.Core/Untitled.canvas",
    "Engine.Core/DsSystem.md",
    "Engine.Core/DsCPU.md",
    "Engine.Core/Core 자료 구조.md",
    "Engine.Core/Core Dll hierarchy.canvas",
    "App Dll Hierarchy.canvas",
    "Global/Common assembly.md",
    "User Defined Structure.md",
    "Others/PLC 생성.md",
    "Others/Powerpoint Addin's.md",
    "TODO's.md",
    "사용자 정의 structure.md",
    "DsWebServer/HMI/Browser UI/WgtGridLampReal.canvas",
    "DsWebServer/HMI/Browser UI/WgtLampRGFH.canvas",
    "DsWebServer/HMI/Browser UI/0. PageHmi.canvas",
    "DsWebServer/HMI/Browser UI/CompHmiButtonColumn.md",
    "DsWebServer/HMI/HMI.md",
    "DsWebServer/HMI/TagWeb.md",
    "DsWebServer/HMI/Browser UI",
    "DsWebServer/IOHub Web 연동.md",
    "Others",
    "0. TOC.md",
    "DsWebServer/Controller.md",
    "DsWebServer/DsWebServer.canvas",
    "IOHub/Endian.md",
    "IOHub/DS runtime.md",
    "IOHub/Client.md",
    "IOHub/Architecture.canvas",
    "IOHub/0. Index.md",
    "IOHub/Requirements.md",
    "IOHub/PLC, Field IO.md",
    "IOHub/Notification.md",
    "IOHub/IOHub.md",
    "Engine.Core",
    "DsWebServer",
    "Stat/Database/Schema.canvas",
    "QuerySet",
    "Stat/개발 concepts",
    "Stat/Database/Tables",
    "Stat/Database",
    "Stat",
    "IOHub/Zmq"
  ]
}